qanty/__init__.py
qanty/client.py
qanty/exceptions.py
qanty/version.py
qanty/common/__init__.py
qanty/common/models.py
qanty-0.1.2.dist-info/LICENSE
qanty-0.1.2.dist-info/METADATA
qanty-0.1.2.dist-info/WHEEL
qanty-0.1.2.dist-info/top_level.txt
qanty-0.1.2.dist-info/RECORD
