Metadata-Version: 2.1
Name: qanty
Version: 0.1.2
Summary: Qanty API Client
Home-page: https://www.qanty.com
Author: Juan F. Duque
Author-email: jfelipe@grupodyd.com
License: MIT
Project-URL: Source, https://github.com/grupodyd/python-qanty
Project-URL: Tracker, https://github.com/grupodyd/python-qanty/issues
Keywords: qanty
Classifier: Development Status :: 2 - Pre-Alpha
Classifier: Environment :: Console
Classifier: Intended Audience :: Developers
Classifier: License :: OSI Approved :: MIT License
Classifier: Operating System :: OS Independent
Classifier: Programming Language :: Python
Classifier: Programming Language :: Python :: 3
Classifier: Programming Language :: Python :: 3 :: Only
Classifier: Programming Language :: Python :: 3.10
Classifier: Programming Language :: Python :: 3.11
Classifier: Programming Language :: Python :: 3.12
Classifier: Programming Language :: Python :: Implementation :: CPython
Classifier: Topic :: Software Development :: Libraries :: Python Modules
Requires-Python: >=3.10.0
License-File: LICENSE
Requires-Dist: httpx[http2] <1,>=0.24.0
Requires-Dist: pydantic <3,>=2
Requires-Dist: python-dateutil <3,>=2.8.2
